{"trial_id": "04", "hyperparameters": {"space": [{"class_name": "Choice", "config": {"name": "l2_reg", "default": 0.0001, "conditions": [], "values": [0.0001, 0.0005], "ordered": true}}, {"class_name": "Choice", "config": {"name": "learning_rate", "default": 0.0001, "conditions": [], "values": [0.0001, 0.0005, 0.001], "ordered": true}}], "values": {"l2_reg": 0.0001, "learning_rate": 0.001}}, "metrics": {"metrics": {"age_output_loss": {"direction": "min", "observations": [{"value": [143.1160430908203], "step": 2}]}, "age_output_mae": {"direction": "min", "observations": [{"value": [9.309651374816895], "step": 2}]}, "gender_output_accuracy": {"direction": "min", "observations": [{"value": [0.8305214643478394], "step": 2}]}, "gender_output_loss": {"direction": "min", "observations": [{"value": [1.2733542919158936], "step": 2}]}, "loss": {"direction": "min", "observations": [{"value": [144.57080078125], "step": 2}]}, "val_age_output_loss": {"direction": "min", "observations": [{"value": [165.78634643554688], "step": 2}]}, "val_age_output_mae": {"direction": "min", "observations": [{"value": [9.640677452087402], "step": 2}]}, "val_gender_output_accuracy": {"direction": "min", "observations": [{"value": [0.7233686447143555], "step": 2}]}, "val_gender_output_loss": {"direction": "min", "observations": [{"value": [2.6339855194091797], "step": 2}]}, "val_loss": {"direction": "min", "observations": [{"value": [167.53514099121094], "step": 2}]}, "multi_objective": {"direction": "min", "observations": [{"value": [8.917308807373047], "step": 2}]}}}, "score": 8.917308807373047, "best_step": 2, "status": "COMPLETED", "message": null}